macholib/MachO.py
macholib/MachOGraph.py
macholib/MachOStandalone.py
macholib/SymbolTable.py
macholib/__init__.py
macholib/__main__.py
macholib/_cmdline.py
macholib/dyld.py
macholib/dylib.py
macholib/framework.py
macholib/itergraphreport.py
macholib/mach_o.py
macholib/macho_dump.py
macholib/macho_find.py
macholib/macho_standalone.py
macholib/ptypes.py
macholib/util.py
macholib-1.15.dist-info/LICENSE
macholib-1.15.dist-info/METADATA
macholib-1.15.dist-info/WHEEL
macholib-1.15.dist-info/entry_points.txt
macholib-1.15.dist-info/top_level.txt
macholib-1.15.dist-info/zip-safe
macholib-1.15.dist-info/RECORD
