Metadata-Version: 2.1
Name: macholib
Version: 1.15
Summary: Mach-O header analysis and editing
Home-page: http://github.com/ronaldoussoren/macholib
Author: Ronald Oussoren
Author-email: ronaldoussoren@mac.com
Maintainer: Ronald Oussoren
Maintainer-email: ronaldoussoren@mac.com
License: MIT
Download-URL: http://pypi.python.org/pypi/macholib
Keywords: Mach-O,,dyld
Platform: any
Classifier: Intended Audience :: Developers
Classifier: License :: OSI Approved :: MIT License
Classifier: Programming Language :: Python
Classifier: Programming Language :: Python :: 2
Classifier: Programming Language :: Python :: 2.7
Classifier: Programming Language :: Python :: 3
Classifier: Programming Language :: Python :: 3.4
Classifier: Programming Language :: Python :: 3.5
Classifier: Programming Language :: Python :: 3.6
Classifier: Programming Language :: Python :: 3.7
Classifier: Programming Language :: Python :: 3.8
Classifier: Programming Language :: Python :: 3.9
Classifier: Operating System :: MacOS :: MacOS X
Classifier: Topic :: Software Development :: Libraries :: Python Modules
Classifier: Topic :: Software Development :: Build Tools
Project-URL: Documentation, https://macholib.readthedocs.io/en/latest/
Project-URL: Issue tracker, https://github.com/ronaldoussoren/macholib/issues
Project-URL: Repository, https://github.com/ronaldoussoren/macholib
